README.md
setup.py
storekeys/__init__.py
storekeys/errors.py
storekeys/load.py
storekeys/store.py
storekeys.egg-info/PKG-INFO
storekeys.egg-info/SOURCES.txt
storekeys.egg-info/dependency_links.txt
storekeys.egg-info/entry_points.txt
storekeys.egg-info/requires.txt
storekeys.egg-info/top_level.txt